LICENSE.txt
MANIFEST.in
README.md
setup.cfg
setup.py
gvSelect/__init__.py
gvSelect/gvSelect.py
gvSelect.egg-info/PKG-INFO
gvSelect.egg-info/SOURCES.txt
gvSelect.egg-info/dependency_links.txt
gvSelect.egg-info/requires.txt
gvSelect.egg-info/top_level.txt