Metadata-Version: 1.1
Name: gvSelect
Version: 1.0
Summary: Read and write gadgetviewer selection files in python
Home-page: https://github.com/simongibbons/gvSelect
Author: Simon Gibbons
Author-email: sljg2@ast.cam.ac.uk
License: UNKNOWN
Download-URL: https://github.com/simongibbons/gvSelect/tarball/v1.0
Keywords: gadget,gadgetviewer
Platform: UNKNOWN
